[
  {
    "encoding": "morton",
    "model": "vqc_linear",
    "n_total_runs": 10,
    "n_success": 10,
    "success_rate": 1.0,
    "mean_val_acc": 0.1,
    "std_val_acc": 0.0,
    "mean_val_acc_legacy_batchmean_unscaled": 0.11363636363636365,
    "std_val_acc_legacy_batchmean_unscaled": 0.0,
    "legacy_metric_note": "legacy comparability only",
    "mean_runtime": 744.1415145397186,
    "stability_score": 0.1,
    "lps": 64.5
  },
  {
    "encoding": "hilbert",
    "model": "vqc_linear",
    "n_total_runs": 10,
    "n_success": 10,
    "success_rate": 1.0,
    "mean_val_acc": 0.1,
    "std_val_acc": 0.0,
    "mean_val_acc_legacy_batchmean_unscaled": 0.11363636363636365,
    "std_val_acc_legacy_batchmean_unscaled": 0.0,
    "legacy_metric_note": "legacy comparability only",
    "mean_runtime": 759.897640633583,
    "stability_score": 0.1,
    "lps": 77.90625
  },
  {
    "encoding": "row_major",
    "model": "vqc_linear",
    "n_total_runs": 10,
    "n_success": 10,
    "success_rate": 1.0,
    "mean_val_acc": 0.1,
    "std_val_acc": 0.0,
    "mean_val_acc_legacy_batchmean_unscaled": 0.11363636363636365,
    "std_val_acc_legacy_batchmean_unscaled": 0.0,
    "legacy_metric_note": "legacy comparability only",
    "mean_runtime": 784.8098157405853,
    "stability_score": 0.1,
    "lps": 64.5
  },
  {
    "encoding": "column_major",
    "model": "vqc_linear",
    "n_total_runs": 10,
    "n_success": 10,
    "success_rate": 1.0,
    "mean_val_acc": 0.1,
    "std_val_acc": 0.0,
    "mean_val_acc_legacy_batchmean_unscaled": 0.11363636363636365,
    "std_val_acc_legacy_batchmean_unscaled": 0.0,
    "legacy_metric_note": "legacy comparability only",
    "mean_runtime": 743.7746910810471,
    "stability_score": 0.1,
    "lps": 64.5
  },
  {
    "encoding": "snake",
    "model": "vqc_linear",
    "n_total_runs": 10,
    "n_success": 10,
    "success_rate": 1.0,
    "mean_val_acc": 0.1,
    "std_val_acc": 0.0,
    "mean_val_acc_legacy_batchmean_unscaled": 0.11363636363636365,
    "std_val_acc_legacy_batchmean_unscaled": 0.0,
    "legacy_metric_note": "legacy comparability only",
    "mean_runtime": 743.9007094621659,
    "stability_score": 0.1,
    "lps": 64.5
  },
  {
    "encoding": "corner_spiral",
    "model": "vqc_linear",
    "n_total_runs": 10,
    "n_success": 10,
    "success_rate": 1.0,
    "mean_val_acc": 0.1,
    "std_val_acc": 0.0,
    "mean_val_acc_legacy_batchmean_unscaled": 0.11363636363636365,
    "std_val_acc_legacy_batchmean_unscaled": 0.0,
    "legacy_metric_note": "legacy comparability only",
    "mean_runtime": 743.995915055275,
    "stability_score": 0.1,
    "lps": 168.515625
  },
  {
    "encoding": "diagonal",
    "model": "vqc_linear",
    "n_total_runs": 10,
    "n_success": 10,
    "success_rate": 1.0,
    "mean_val_acc": 0.1,
    "std_val_acc": 0.0,
    "mean_val_acc_legacy_batchmean_unscaled": 0.11363636363636365,
    "std_val_acc_legacy_batchmean_unscaled": 0.0,
    "legacy_metric_note": "legacy comparability only",
    "mean_runtime": 743.9765320301055,
    "stability_score": 0.1,
    "lps": 85.5
  },
  {
    "encoding": "diagonal_zigzag",
    "model": "vqc_linear",
    "n_total_runs": 10,
    "n_success": 10,
    "success_rate": 1.0,
    "mean_val_acc": 0.1,
    "std_val_acc": 0.0,
    "mean_val_acc_legacy_batchmean_unscaled": 0.11363636363636365,
    "std_val_acc_legacy_batchmean_unscaled": 0.0,
    "legacy_metric_note": "legacy comparability only",
    "mean_runtime": 744.1114156961441,
    "stability_score": 0.1,
    "lps": 85.5
  },
  {
    "encoding": "vertical_snake",
    "model": "vqc_linear",
    "n_total_runs": 10,
    "n_success": 10,
    "success_rate": 1.0,
    "mean_val_acc": 0.1,
    "std_val_acc": 0.0,
    "mean_val_acc_legacy_batchmean_unscaled": 0.11363636363636365,
    "std_val_acc_legacy_batchmean_unscaled": 0.0,
    "legacy_metric_note": "legacy comparability only",
    "mean_runtime": 743.8495082139968,
    "stability_score": 0.1,
    "lps": 64.5
  }
]